examples/__init__.py
examples/gpio_detect.py
examples/joystick.py
examples/light_circle_abort.py
examples/light_simple_cross.py
examples/mark_square.py
examples/position_sync_grid.py
galvo/__init__.py
galvo/consts.py
galvo/controller.py
galvo/mock_connection.py
galvo/usb_connection.py
test/__init__.py
test/test_api.py
test/test_co2.py
galvoplotter-0.2.0.dist-info/LICENSE
galvoplotter-0.2.0.dist-info/METADATA
galvoplotter-0.2.0.dist-info/WHEEL
galvoplotter-0.2.0.dist-info/top_level.txt
galvoplotter-0.2.0.dist-info/zip-safe
galvoplotter-0.2.0.dist-info/RECORD
