Metadata-Version: 2.1
Name: galvoplotter
Version: 0.2.0
Summary: Galvo Plotter
Home-page: https://github.com/meerk40t/galvoplotter
Author: Tatarize
Author-email: tatarize@gmail.com
License: MIT
Keywords: ezcad2,galvo,laser
Classifier: Development Status :: 4 - Beta
Classifier: License :: OSI Approved :: MIT License
Classifier: Operating System :: OS Independent
Classifier: Programming Language :: Python
Classifier: Programming Language :: Python :: 3.6
Classifier: Programming Language :: Python :: 3.7
Classifier: Programming Language :: Python :: 3.8
Classifier: Programming Language :: Python :: 3.9
Classifier: Programming Language :: Python :: 3.10
Classifier: Programming Language :: Python :: 3.11
Classifier: Topic :: Utilities
License-File: LICENSE
Requires-Dist: pyusb
